[{"geo": "tris:shirt_low", "node": "tris:shirt_low_skinClst", "jnts": ["HipPart1_R", "HipPart2_R", "Knee_R", "Ankle_R", "Toes_R", "ToesEnd_R", "RootPart1_M", "RootPart2_M", "Spine1_M", "Spine1Part1_M", "Spine1Part2_M", "Chest_M", "Scapula_R", "Hip_R", "Root_M", "ToesEnd_L", "Toes_L", "Ankle_L", "Knee_L", "HipPart2_L", "HipPart1_L", "Hip_L", "Scapula_L", "Shoulder_L", "Shoulder_R", "Lf_legArmor", "Rt_legArmor"], "wiJnts": ["HipPart1_R", "HipPart2_R", "Knee_R", "Ankle_R", "RootPart1_M", "RootPart2_M", "Spine1_M", "Spine1Part1_M", "Spine1Part2_M", "Chest_M", "Scapula_R", "Hip_R", "Root_M", "Ankle_L", "Knee_L", "HipPart2_L", "HipPart1_L", "Hip_L", "Scapula_L", "Shoulder_L", "Shoulder_R", "Lf_legArmor", "Rt_legArmor"], "maxi": 4, "method": 0}]